PolygonCall.py
__init__.py
polygon_call-1.0.0.dist-info/METADATA
polygon_call-1.0.0.dist-info/WHEEL
polygon_call-1.0.0.dist-info/top_level.txt
polygon_call-1.0.0.dist-info/RECORD
