Metadata-Version: 2.1
Name: polygon-call
Version: 1.0.0
Summary: Repeatedly calls the polygon api every 1 seconds for 24 hours
Home-page: UNKNOWN
Author: Yuqi Tang
Author-email: yt2101@nyu.edu
License: UNKNOWN
Platform: UNKNOWN
